{
  "updatedAt": "2026-03-04",
  "services": [
    {
      "key": "job-hunter",
      "name": "Job Hunter",
      "type": "Bot + Dashboard",
      "status": "unknown",
      "primaryUrl": "https://job-hunter-bot-two.vercel.app",
      "notes": "CRM + tailoring + doc proxy."
    },
    {
      "key": "polymarket",
      "name": "Polymarket Stack",
      "type": "Bot + Dashboard",
      "status": "unknown",
      "primaryUrl": "https://github.com/dktrn9ne/Fresh-dashboard",
      "notes": "Bot health/events/ledger; Vercel dashboard."
    },
    {
      "key": "myspace",
      "name": "MySpace Resume",
      "type": "Site",
      "status": "online",
      "primaryUrl": "https://myspace-resume.vercel.app",
      "notes": "Public site."
    }
  ]
}
